ddlogs/__init__.py
ddlogs-0.2.0.dist-info/LICENSE
ddlogs-0.2.0.dist-info/METADATA
ddlogs-0.2.0.dist-info/WHEEL
ddlogs-0.2.0.dist-info/top_level.txt
ddlogs-0.2.0.dist-info/RECORD
