Metadata-Version: 2.1
Name: ddlogs
Version: 0.2.0
Summary: Datadog Logs logging handler and utilities
Home-page: https://github.com/marcy-terui/ddlogs
Author: Masashi Terui
Author-email: marcy9114+pypi@gmail.com
License: MIT License
Keywords: datadog logs logging handler
Platform: UNKNOWN
Classifier: Development Status :: 4 - Beta
Classifier: Intended Audience :: Developers
Classifier: License :: OSI Approved :: MIT License
Classifier: Programming Language :: Python
Classifier: Programming Language :: Python :: 2.7
Classifier: Programming Language :: Python :: 3
